ln_fibonacci/__init__.py
ln_fibonacci/fibonacci.py
ln_fibonacci-0.0.1.dist-info/LICENSE.txt
ln_fibonacci-0.0.1.dist-info/METADATA
ln_fibonacci-0.0.1.dist-info/WHEEL
ln_fibonacci-0.0.1.dist-info/top_level.txt
ln_fibonacci-0.0.1.dist-info/RECORD
