Metadata-Version: 2.1
Name: ln-fibonacci
Version: 0.0.1
Summary: for quiz 4
Author: luka_namgaladze
Author-email: luka.namgaladze7@gmail.com
Classifier: Programming Language :: Python :: 3
Classifier: License :: OSI Approved :: MIT License
Classifier: Operating System :: OS Independent
Requires-Python: >=3.6
License-File: LICENSE.txt
